discord/ext/dash/__init__.py
discord/ext/dash/dashboard.py
discord/ext/dash/errors.py
discord/ext/dash/server.py
discord_ext_dash-0.3.1.dist-info/METADATA
discord_ext_dash-0.3.1.dist-info/WHEEL
discord_ext_dash-0.3.1.dist-info/top_level.txt
discord_ext_dash-0.3.1.dist-info/RECORD
