Metadata-Version: 2.1
Name: discord-ext-dash
Version: 0.3.1
Summary: A webhook and request based discord.py extension for making a bot dashboard.
Home-page: https://github.com/timoo4devv/discord-ext-dash
Author: Timo
License: MIT
Classifier: Development Status :: 5 - Production/Stable
Classifier: License :: OSI Approved :: MIT License
Classifier: Intended Audience :: Developers
Classifier: Natural Language :: English
Classifier: Operating System :: OS Independent
Classifier: Programming Language :: Python :: 3.5
Classifier: Programming Language :: Python :: 3.6
Classifier: Programming Language :: Python :: 3.7
Classifier: Programming Language :: Python :: 3.8
Classifier: Topic :: Internet
Classifier: Topic :: Software Development :: Libraries
Classifier: Topic :: Software Development :: Libraries :: Python Modules
Classifier: Topic :: Utilities
Requires-Python: >=3.5.3
Requires-Dist: discord.py >=1.5.1
